memoria/__init__.py
memoria/cache/__init__.py
memoria/cache/cache.py
memoria/cache/set_cache_dir.py
memoria/hash/__init__.py
memoria/hash/make_hashable.py
memoria-2025.4.27.4.dist-info/METADATA
memoria-2025.4.27.4.dist-info/WHEEL
memoria-2025.4.27.4.dist-info/licenses/LICENSE
memoria-2025.4.27.4.dist-info/RECORD
